setup.py
FA/__init__.py
FA/Categories/Categorizer.py
FA/Categories/MainCategories.py
FA/Categories/Models.py
FA/Categories/SubCategories.py
FA/Categories/__init__.py
FA/JDownloader/__init__.py
FA/JEngines/Categorizer.py
FA/JEngines/CategoryEngine.py
FA/JEngines/TickerEngine.py
FA/JEngines/VRNameEngine.py
FA/JEngines/__init__.py
FA/JEngines/JarticleEnhancer/Enhancers.py
FA/JEngines/JarticleEnhancer/JProcess.py
FA/JEngines/JarticleEnhancer/MetaEnhancers.py
FA/JEngines/JarticleEnhancer/__init__.py
FA/JHelpers/ART.py
FA/JHelpers/NLTK.py
FA/JHelpers/PageRank.py
FA/JHelpers/Validator.py
FA/JHelpers/__init__.py
FA/JHelpers/artSort.py
FA/JModel/JArticle.py
FA/JModel/Models.py
FA/JModel/__init__.py
FAui/ViewElements.py
FAui/__init__.py
FAui/jarticleInstall.sh
FAui/jarticleMain.py
FAui/mainw.ui
FAui/MongoQ/__init__.py
FairArticle.egg-info/PKG-INFO
FairArticle.egg-info/SOURCES.txt
FairArticle.egg-info/dependency_links.txt
FairArticle.egg-info/requires.txt
FairArticle.egg-info/top_level.txt